jwrite
jread
