Metadata-Version: 1.0
Name: pjtree
Version: 0.1.0
Summary: Create files script.
Home-page: https://github.com/corrupt952/pjtree
Author: Kazuki Hasegawa
Author-email: hasegawa_0204@hotmail.co.jp
License: BSD
Platform: UNKNOWN
Classifier: Programming Language :: Python
Classifier: Programming Language :: Python :: 2.7
Classifier: Programming Language :: Python :: 3.3
Classifier: Operating System :: OS Independent
Classifier: Development Status :: 2 - Pre-Alpha
Classifier: License :: OSI Approved :: BSD License
